aioify/__init__.py
aioify/__init__.pyi
aioify-0.4.1.dist-info/LICENSE.txt
aioify-0.4.1.dist-info/WHEEL
aioify-0.4.1.dist-info/METADATA
aioify-0.4.1.dist-info/RECORD
