Metadata-Version: 2.1
Name: aioify
Version: 0.4.1
Summary: Make every Python function async/await
Home-page: https://github.com/yifeikong/aioify
License: MIT
Keywords: asyncio,async,await,aioify,wrap
Author: Yifei Kong
Author-email: kongyifei@gmail.com
Requires-Python: >=3.6,<3.10
Classifier: Development Status :: 7 - Inactive
Classifier: Intended Audience :: Developers
Classifier: License :: OSI Approved :: MIT License
Classifier: Programming Language :: Python :: 3
Classifier: Programming Language :: Python :: 3.6
Classifier: Programming Language :: Python :: 3.7
Classifier: Programming Language :: Python :: 3.8
Classifier: Programming Language :: Python :: 3.9
Requires-Dist: module-wrapper (>=0.3.0,<0.4.0)
Project-URL: Repository, https://github.com/yifeikong/aioify
